Cipherbcryptor.py
cipherbcryptor-1.3.dist-info/LICENSE
cipherbcryptor-1.3.dist-info/METADATA
cipherbcryptor-1.3.dist-info/WHEEL
cipherbcryptor-1.3.dist-info/RECORD
